data_transformation_tc.py
data_transformation_tc-0.1.7.dist-info/entry_points.txt
data_transformation_tc-0.1.7.dist-info/WHEEL
data_transformation_tc-0.1.7.dist-info/METADATA
data_transformation_tc-0.1.7.dist-info/RECORD
